csvtodat.py
csvtodat-0.2.0.dist-info/LICENSE.txt
csvtodat-0.2.0.dist-info/METADATA
csvtodat-0.2.0.dist-info/WHEEL
csvtodat-0.2.0.dist-info/top_level.txt
csvtodat-0.2.0.dist-info/RECORD
